{"_type": "person", "death_date": null, "contact_details": [], "_meta": {}, "links": [{"note": "homepage", "url": "http://www.cesarpalacio.com"}], "sources": [{"url": "http://app.toronto.ca/im/council/councillors.jsp", "note": null}, {"url": "http://www.toronto.ca/councillors/palacio1.htm", "note": null}], "gender": null, "image": null, "identifiers": [], "other_names": [], "summary": null, "post_id": "Ward 17 Davenport", "extras": {}, "chamber": null, "birth_date": null, "party": null, "_id": "e9323163-0433-11e3-9f05-b8f6b115fc07", "biography": null, "name": "Cesar Palacio"}